django_hats/.DS_Store
django_hats/__init__.py
django_hats/__init__.pyc
django_hats/apps.py
django_hats/apps.pyc
django_hats/bootstrap.py
django_hats/bootstrap.pyc
django_hats/context_processors.py
django_hats/context_processors.pyc
django_hats/mixins.py
django_hats/mixins.pyc
django_hats/roles.py
django_hats/roles.pyc
django_hats/signals.py
django_hats/signals.pyc
django_hats/utils.py
django_hats/utils.pyc
django_hats/__pycache__/__init__.cpython-35.pyc
django_hats/__pycache__/apps.cpython-35.pyc
django_hats/__pycache__/bootstrap.cpython-35.pyc
django_hats/__pycache__/context_processors.cpython-35.pyc
django_hats/__pycache__/mixins.cpython-35.pyc
django_hats/__pycache__/roles.cpython-35.pyc
django_hats/__pycache__/signals.cpython-35.pyc
django_hats/__pycache__/utils.cpython-35.pyc
django_hats/management/.DS_Store
django_hats/management/__init__.py
django_hats/management/__init__.pyc
django_hats/management/__pycache__/__init__.cpython-35.pyc
django_hats/management/commands/__init__.py
django_hats/management/commands/__init__.pyc
django_hats/management/commands/cleanup_roles.py
django_hats/management/commands/cleanup_roles.pyc
django_hats/management/commands/migrate_role.py
django_hats/management/commands/migrate_role.pyc
django_hats/management/commands/synchronize_roles.py
django_hats/management/commands/synchronize_roles.pyc
django_hats/management/commands/__pycache__/__init__.cpython-35.pyc
django_hats/management/commands/__pycache__/cleanup_roles.cpython-35.pyc
django_hats/management/commands/__pycache__/migrate_role.cpython-35.pyc
django_hats/management/commands/__pycache__/synchronize_roles.cpython-35.pyc
django_hats/templatetags/.DS_Store
django_hats/templatetags/__init__.py
django_hats/templatetags/__init__.pyc
django_hats/templatetags/roles.py
django_hats/templatetags/roles.pyc
django_hats/templatetags/__pycache__/__init__.cpython-35.pyc
django_hats/templatetags/__pycache__/roles.cpython-35.pyc
django_hats-1.1.2.dist-info/DESCRIPTION.rst
django_hats-1.1.2.dist-info/METADATA
django_hats-1.1.2.dist-info/metadata.json
django_hats-1.1.2.dist-info/RECORD
django_hats-1.1.2.dist-info/top_level.txt
django_hats-1.1.2.dist-info/WHEEL
