Metadata-Version: 2.0
Name: django-hats
Version: 1.1.2
Summary: Role-based permissions system for Django. Everyone wears a different hat, some people wear multiple.
Home-page: https://github.com/GenePeeks/django-hats
Author: Mike Hearing
Author-email: mhearing@genepeeks.com
License: MIT License
Platform: UNKNOWN
Classifier: Development Status :: 5 - Production/Stable
Classifier: Environment :: Web Environment
Classifier: Framework :: Django
Classifier: Intended Audience :: Developers
Classifier: License :: OSI Approved :: MIT License
Classifier: Operating System :: OS Independent
Classifier: Programming Language :: Python
Classifier: Programming Language :: Python :: 2.7
Classifier: Programming Language :: Python :: 3.5
Classifier: Topic :: Security
Classifier: Topic :: Software Development :: Libraries :: Application Frameworks
Requires-Dist: django (>=1.9.0)
